README.md
setup.py
likewines.egg-info/PKG-INFO
likewines.egg-info/SOURCES.txt
likewines.egg-info/dependency_links.txt
likewines.egg-info/requires.txt
likewines.egg-info/top_level.txt
model/__init__.py
model/compare_model.py
model/predict_model.py
processor/__init__.py
processor/compare_data_processor.py
processor/predict_data_processor.py