Metadata-Version: 2.1
Name: likewines
Version: 0.1.1
Summary: Comparison and predictive analysis of wines
Author: Ngoc Minh Ngo
